FastDebugger/__init__.py
FastDebugger/fast_debugger.py
FastDebugger-0.0.43.dist-info/LICENSE
FastDebugger-0.0.43.dist-info/METADATA
FastDebugger-0.0.43.dist-info/WHEEL
FastDebugger-0.0.43.dist-info/top_level.txt
FastDebugger-0.0.43.dist-info/RECORD
