Metadata-Version: 2.1
Name: FastDebugger
Version: 0.0.43
Summary: Fast debugger for Python 3
Home-page: https://github.com/RasseTheBoy/FastDebugger
Author: Rasmus Ohert
Author-email: Rasmus Ohert <rassemichael@gmail.com>
Project-URL: Homepage, https://github.com/RasseTheBoy/FastDebugger
Classifier: Development Status :: 5 - Production/Stable
Classifier: Intended Audience :: Education
Classifier: Programming Language :: Python :: 3
Classifier: Operating System :: OS Independent
Classifier: License :: OSI Approved :: MIT License
Requires-Python: >=3.7
License-File: LICENSE
Requires-Dist: colored
Requires-Dist: asttokens
Requires-Dist: executing
